kakaobot/__init__.py
kakaobot/kboard.py
kakaobot/log_append.py
kakaobot/mbutton.py
kakaobot/message.py
kakaobot/photo.py
kakaobot/resp_param.py
kakaobot.py-1.1.dist-info/METADATA
kakaobot.py-1.1.dist-info/RECORD
kakaobot.py-1.1.dist-info/WHEEL
kakaobot.py-1.1.dist-info/top_level.txt
