Metadata-Version: 2.1
Name: kakaobot.py
Version: 1.1
Summary: API wrapper for Kakaotalk written in Python.
Home-page: https://github.com/Katinor/kakaobot.py
Author: Katinor
Author-email: katinor@4ears.net
License: MIT
Download-URL: https://github.com/Katinor/kakaobot.py
Keywords: kakaotalk,chatbot,api
Platform: UNKNOWN
Classifier: Development Status :: 5 - Production/Stable
Classifier: License :: OSI Approved :: MIT License
Classifier: Intended Audience :: Developers
Classifier: Topic :: Communications :: Chat
Classifier: Framework :: Flask
Classifier: Natural Language :: Korean
Classifier: Programming Language :: Python :: 3 :: Only
Requires-Python: >=3
Requires-Dist: Flask (==1.0.2)
